README.md
license.txt
setup.py
Get_API_Blaze.egg-info/PKG-INFO
Get_API_Blaze.egg-info/SOURCES.txt
Get_API_Blaze.egg-info/dependency_links.txt
Get_API_Blaze.egg-info/top_level.txt
Get_API_blaze/__init__.py
Get_API_blaze/results_gather.py