Metadata-Version: 2.1
Name: Get-API-Blaze
Version: 1.0
Summary: This package facilitates the data collection process directly from the blaze API by generating a list or a dictionary to work more easily with the blaze double or crash data.
Author: Ramon
Author-email: ramonma31@gmail.com
Keywords: blaze,api,get api,double,crash
License-File: license.txt
